{
    "device": "GPU: NVIDIA GeForce RTX 4060 | MEMORY: 8585216000 | COMPUTE: (8, 9)",
    "batch_size": 128,
    "epochs": 400,
    "about": [
        "[DATASET]",
        "   MNIST: images of handwritten digits of shape [1,28,28]",
        "   Train dataset length: 60000",
        "   Test dataset length: 10000",
        "   Classes: 10",
        "[MODEL]",
        "   DCGAN architecture adapted to MNIST images",
        "   Generator LR: 2e-4 betas=(0.5, 0.999)",
        "   Discriminator LR: 1e-4 betas=(0.5, 0.999)",
        "   LOSS: BCELoss",
        "[TRAINING]",
        "   Generator Discriminator trained 1 per epoch",
        "   Discriminator taught real images are real 100%",
        "   Discriminator taught fake images are fake 100%",
        "[RESULTS]",
        "[IMPROVEMENTS]",
        "   1. Initialize the weights according to DCGAN paper (Page 3-4)"
    ],
    "train_durations": [
        "[cuda] Epochs: 10 Training time: 0h - 2min - 9s",
        "[cuda] Epochs: 50 Training time: 0h - 10min - 55s",
        "[cuda] Epochs: 150 Training time: 0h - 34min - 1s",
        "[cuda] Epochs: 90 Training time: 0h - 19min - 55s",
        "[cuda] Epochs: 100 Training time: 0h - 22min - 8s"
    ],
    "results": [
        "[D LOSS]: 0.3752 [G LOSS]: 1.7793 [D Acc REAL]: 72.78% [D Acc FAKE]: 24.41% [D Acc REAL - TEST]: 91.20%",
        "[D LOSS]: 0.3529 [G LOSS]: 2.0601 [D Acc REAL]: 75.88% [D Acc FAKE]: 22.37% [D Acc REAL - TEST]: 92.43%",
        "[D LOSS]: 0.3632 [G LOSS]: 2.1339 [D Acc REAL]: 75.85% [D Acc FAKE]: 22.36% [D Acc REAL - TEST]: 62.01%",
        "[D LOSS]: 0.3560 [G LOSS]: 2.2121 [D Acc REAL]: 76.48% [D Acc FAKE]: 21.76% [D Acc REAL - TEST]: 90.74%",
        "[D LOSS]: 0.3692 [G LOSS]: 2.2368 [D Acc REAL]: 76.13% [D Acc FAKE]: 22.02% [D Acc REAL - TEST]: 68.16%",
        "[D LOSS]: 0.3823 [G LOSS]: 2.1831 [D Acc REAL]: 75.41% [D Acc FAKE]: 22.48% [D Acc REAL - TEST]: 72.50%",
        "[D LOSS]: 0.3906 [G LOSS]: 2.1523 [D Acc REAL]: 74.93% [D Acc FAKE]: 22.94% [D Acc REAL - TEST]: 94.12%",
        "[D LOSS]: 0.3861 [G LOSS]: 2.1543 [D Acc REAL]: 75.17% [D Acc FAKE]: 22.51% [D Acc REAL - TEST]: 84.52%",
        "[D LOSS]: 0.3984 [G LOSS]: 2.1637 [D Acc REAL]: 74.77% [D Acc FAKE]: 22.81% [D Acc REAL - TEST]: 86.97%",
        "[D LOSS]: 0.4027 [G LOSS]: 2.1174 [D Acc REAL]: 74.48% [D Acc FAKE]: 22.89% [D Acc REAL - TEST]: 64.48%",
        "[D LOSS]: 0.4041 [G LOSS]: 2.0953 [D Acc REAL]: 74.22% [D Acc FAKE]: 23.31% [D Acc REAL - TEST]: 73.16%",
        "[D LOSS]: 0.4054 [G LOSS]: 2.0967 [D Acc REAL]: 74.13% [D Acc FAKE]: 23.24% [D Acc REAL - TEST]: 70.44%",
        "[D LOSS]: 0.3983 [G LOSS]: 2.1124 [D Acc REAL]: 74.36% [D Acc FAKE]: 23.16% [D Acc REAL - TEST]: 80.69%",
        "[D LOSS]: 0.4032 [G LOSS]: 2.1247 [D Acc REAL]: 74.27% [D Acc FAKE]: 23.03% [D Acc REAL - TEST]: 79.45%",
        "[D LOSS]: 0.3958 [G LOSS]: 2.1499 [D Acc REAL]: 74.74% [D Acc FAKE]: 22.65% [D Acc REAL - TEST]: 64.59%",
        "[D LOSS]: 0.4035 [G LOSS]: 2.1322 [D Acc REAL]: 74.40% [D Acc FAKE]: 22.91% [D Acc REAL - TEST]: 76.89%",
        "[D LOSS]: 0.3968 [G LOSS]: 2.1531 [D Acc REAL]: 74.71% [D Acc FAKE]: 22.71% [D Acc REAL - TEST]: 64.32%",
        "[D LOSS]: 0.4033 [G LOSS]: 2.1664 [D Acc REAL]: 74.56% [D Acc FAKE]: 22.65% [D Acc REAL - TEST]: 66.57%",
        "[D LOSS]: 0.3923 [G LOSS]: 2.1829 [D Acc REAL]: 74.84% [D Acc FAKE]: 22.41% [D Acc REAL - TEST]: 77.84%",
        "[D LOSS]: 0.3977 [G LOSS]: 2.1922 [D Acc REAL]: 74.66% [D Acc FAKE]: 22.54% [D Acc REAL - TEST]: 87.77%",
        "[D LOSS]: 0.3916 [G LOSS]: 2.1791 [D Acc REAL]: 74.85% [D Acc FAKE]: 22.36% [D Acc REAL - TEST]: 89.14%",
        "[D LOSS]: 0.3952 [G LOSS]: 2.1843 [D Acc REAL]: 74.84% [D Acc FAKE]: 22.44% [D Acc REAL - TEST]: 63.98%",
        "[D LOSS]: 0.3942 [G LOSS]: 2.2140 [D Acc REAL]: 74.92% [D Acc FAKE]: 22.29% [D Acc REAL - TEST]: 89.06%",
        "[D LOSS]: 0.3854 [G LOSS]: 2.2300 [D Acc REAL]: 75.36% [D Acc FAKE]: 21.86% [D Acc REAL - TEST]: 81.34%",
        "[D LOSS]: 0.3881 [G LOSS]: 2.2415 [D Acc REAL]: 75.20% [D Acc FAKE]: 22.14% [D Acc REAL - TEST]: 69.88%",
        "[D LOSS]: 0.3875 [G LOSS]: 2.2528 [D Acc REAL]: 75.29% [D Acc FAKE]: 21.75% [D Acc REAL - TEST]: 82.83%",
        "[D LOSS]: 0.3901 [G LOSS]: 2.2644 [D Acc REAL]: 75.33% [D Acc FAKE]: 21.85% [D Acc REAL - TEST]: 69.32%",
        "[D LOSS]: 0.3914 [G LOSS]: 2.2383 [D Acc REAL]: 75.08% [D Acc FAKE]: 21.97% [D Acc REAL - TEST]: 87.24%",
        "[D LOSS]: 0.3770 [G LOSS]: 2.2939 [D Acc REAL]: 75.80% [D Acc FAKE]: 21.45% [D Acc REAL - TEST]: 94.49%",
        "[D LOSS]: 0.3835 [G LOSS]: 2.3213 [D Acc REAL]: 75.84% [D Acc FAKE]: 21.53% [D Acc REAL - TEST]: 61.22%",
        "[D LOSS]: 0.3818 [G LOSS]: 2.2773 [D Acc REAL]: 75.60% [D Acc FAKE]: 21.44% [D Acc REAL - TEST]: 82.92%",
        "[D LOSS]: 0.3782 [G LOSS]: 2.3372 [D Acc REAL]: 76.05% [D Acc FAKE]: 21.22% [D Acc REAL - TEST]: 79.68%",
        "[D LOSS]: 0.3742 [G LOSS]: 2.3372 [D Acc REAL]: 76.20% [D Acc FAKE]: 20.97% [D Acc REAL - TEST]: 74.92%",
        "[D LOSS]: 0.3741 [G LOSS]: 2.3490 [D Acc REAL]: 76.23% [D Acc FAKE]: 20.98% [D Acc REAL - TEST]: 90.76%",
        "[D LOSS]: 0.3723 [G LOSS]: 2.3679 [D Acc REAL]: 76.45% [D Acc FAKE]: 20.77% [D Acc REAL - TEST]: 57.44%",
        "[D LOSS]: 0.3739 [G LOSS]: 2.3790 [D Acc REAL]: 76.33% [D Acc FAKE]: 21.01% [D Acc REAL - TEST]: 97.30%",
        "[D LOSS]: 0.3749 [G LOSS]: 2.3662 [D Acc REAL]: 76.34% [D Acc FAKE]: 20.73% [D Acc REAL - TEST]: 63.96%",
        "[D LOSS]: 0.3742 [G LOSS]: 2.3725 [D Acc REAL]: 76.27% [D Acc FAKE]: 20.86% [D Acc REAL - TEST]: 50.85%",
        "[D LOSS]: 0.3662 [G LOSS]: 2.3935 [D Acc REAL]: 76.65% [D Acc FAKE]: 20.46% [D Acc REAL - TEST]: 77.59%",
        "[D LOSS]: 0.3679 [G LOSS]: 2.4269 [D Acc REAL]: 76.81% [D Acc FAKE]: 20.20% [D Acc REAL - TEST]: 36.47%",
        "[D LOSS]: 0.3698 [G LOSS]: 2.4232 [D Acc REAL]: 76.72% [D Acc FAKE]: 20.44% [D Acc REAL - TEST]: 68.26%",
        "[D LOSS]: 0.3661 [G LOSS]: 2.4123 [D Acc REAL]: 76.77% [D Acc FAKE]: 20.45% [D Acc REAL - TEST]: 58.34%",
        "[D LOSS]: 0.3674 [G LOSS]: 2.4212 [D Acc REAL]: 76.66% [D Acc FAKE]: 20.33% [D Acc REAL - TEST]: 81.45%",
        "[D LOSS]: 0.3707 [G LOSS]: 2.4265 [D Acc REAL]: 76.66% [D Acc FAKE]: 20.51% [D Acc REAL - TEST]: 80.14%",
        "[D LOSS]: 0.3694 [G LOSS]: 2.4004 [D Acc REAL]: 76.69% [D Acc FAKE]: 20.46% [D Acc REAL - TEST]: 81.14%",
        "[D LOSS]: 0.3671 [G LOSS]: 2.4187 [D Acc REAL]: 76.73% [D Acc FAKE]: 20.38% [D Acc REAL - TEST]: 59.10%",
        "[D LOSS]: 0.3545 [G LOSS]: 2.4515 [D Acc REAL]: 77.28% [D Acc FAKE]: 19.96% [D Acc REAL - TEST]: 92.05%",
        "[D LOSS]: 0.3722 [G LOSS]: 2.4356 [D Acc REAL]: 76.69% [D Acc FAKE]: 20.63% [D Acc REAL - TEST]: 47.11%",
        "[D LOSS]: 0.3594 [G LOSS]: 2.4528 [D Acc REAL]: 77.09% [D Acc FAKE]: 20.01% [D Acc REAL - TEST]: 59.15%",
        "[D LOSS]: 0.3548 [G LOSS]: 2.4827 [D Acc REAL]: 77.48% [D Acc FAKE]: 19.64% [D Acc REAL - TEST]: 83.20%",
        "[D LOSS]: 0.3626 [G LOSS]: 2.4937 [D Acc REAL]: 77.16% [D Acc FAKE]: 20.04% [D Acc REAL - TEST]: 61.94%",
        "[D LOSS]: 0.3614 [G LOSS]: 2.4970 [D Acc REAL]: 77.19% [D Acc FAKE]: 20.02% [D Acc REAL - TEST]: 71.71%",
        "[D LOSS]: 0.3554 [G LOSS]: 2.5057 [D Acc REAL]: 77.51% [D Acc FAKE]: 19.63% [D Acc REAL - TEST]: 75.28%",
        "[D LOSS]: 0.3626 [G LOSS]: 2.4897 [D Acc REAL]: 77.19% [D Acc FAKE]: 20.00% [D Acc REAL - TEST]: 54.09%",
        "[D LOSS]: 0.3602 [G LOSS]: 2.5226 [D Acc REAL]: 77.31% [D Acc FAKE]: 19.88% [D Acc REAL - TEST]: 60.84%",
        "[D LOSS]: 0.3588 [G LOSS]: 2.4894 [D Acc REAL]: 77.30% [D Acc FAKE]: 19.79% [D Acc REAL - TEST]: 88.23%",
        "[D LOSS]: 0.3516 [G LOSS]: 2.5114 [D Acc REAL]: 77.62% [D Acc FAKE]: 19.28% [D Acc REAL - TEST]: 86.97%",
        "[D LOSS]: 0.3606 [G LOSS]: 2.5359 [D Acc REAL]: 77.44% [D Acc FAKE]: 19.60% [D Acc REAL - TEST]: 68.43%",
        "[D LOSS]: 0.3485 [G LOSS]: 2.5289 [D Acc REAL]: 77.76% [D Acc FAKE]: 19.45% [D Acc REAL - TEST]: 92.54%",
        "[D LOSS]: 0.3447 [G LOSS]: 2.5741 [D Acc REAL]: 78.07% [D Acc FAKE]: 18.97% [D Acc REAL - TEST]: 50.10%",
        "[D LOSS]: 0.3644 [G LOSS]: 2.5307 [D Acc REAL]: 77.23% [D Acc FAKE]: 20.00% [D Acc REAL - TEST]: 66.60%",
        "[D LOSS]: 0.3532 [G LOSS]: 2.5291 [D Acc REAL]: 77.70% [D Acc FAKE]: 19.44% [D Acc REAL - TEST]: 79.98%",
        "[D LOSS]: 0.3604 [G LOSS]: 2.5228 [D Acc REAL]: 77.28% [D Acc FAKE]: 19.66% [D Acc REAL - TEST]: 85.83%",
        "[D LOSS]: 0.3485 [G LOSS]: 2.5512 [D Acc REAL]: 77.93% [D Acc FAKE]: 19.31% [D Acc REAL - TEST]: 53.29%",
        "[D LOSS]: 0.3494 [G LOSS]: 2.5710 [D Acc REAL]: 77.96% [D Acc FAKE]: 19.28% [D Acc REAL - TEST]: 70.84%",
        "[D LOSS]: 0.3557 [G LOSS]: 2.5374 [D Acc REAL]: 77.60% [D Acc FAKE]: 19.44% [D Acc REAL - TEST]: 79.51%",
        "[D LOSS]: 0.3518 [G LOSS]: 2.5654 [D Acc REAL]: 77.82% [D Acc FAKE]: 19.26% [D Acc REAL - TEST]: 62.56%",
        "[D LOSS]: 0.3491 [G LOSS]: 2.5676 [D Acc REAL]: 77.97% [D Acc FAKE]: 19.00% [D Acc REAL - TEST]: 74.38%",
        "[D LOSS]: 0.3523 [G LOSS]: 2.5494 [D Acc REAL]: 77.79% [D Acc FAKE]: 19.28% [D Acc REAL - TEST]: 58.71%",
        "[D LOSS]: 0.3533 [G LOSS]: 2.5475 [D Acc REAL]: 77.73% [D Acc FAKE]: 19.25% [D Acc REAL - TEST]: 32.68%",
        "[D LOSS]: 0.3539 [G LOSS]: 2.5838 [D Acc REAL]: 77.75% [D Acc FAKE]: 19.18% [D Acc REAL - TEST]: 85.03%",
        "[D LOSS]: 0.3576 [G LOSS]: 2.5374 [D Acc REAL]: 77.61% [D Acc FAKE]: 19.34% [D Acc REAL - TEST]: 43.36%",
        "[D LOSS]: 0.3524 [G LOSS]: 2.5453 [D Acc REAL]: 77.79% [D Acc FAKE]: 19.32% [D Acc REAL - TEST]: 64.79%",
        "[D LOSS]: 0.3540 [G LOSS]: 2.5431 [D Acc REAL]: 77.68% [D Acc FAKE]: 19.39% [D Acc REAL - TEST]: 68.23%",
        "[D LOSS]: 0.3494 [G LOSS]: 2.5716 [D Acc REAL]: 77.94% [D Acc FAKE]: 19.12% [D Acc REAL - TEST]: 69.09%",
        "[D LOSS]: 0.3480 [G LOSS]: 2.5653 [D Acc REAL]: 77.98% [D Acc FAKE]: 19.14% [D Acc REAL - TEST]: 63.41%",
        "[D LOSS]: 0.3539 [G LOSS]: 2.5650 [D Acc REAL]: 77.72% [D Acc FAKE]: 19.29% [D Acc REAL - TEST]: 55.39%",
        "[D LOSS]: 0.3402 [G LOSS]: 2.5988 [D Acc REAL]: 78.28% [D Acc FAKE]: 18.82% [D Acc REAL - TEST]: 80.77%",
        "[D LOSS]: 0.3547 [G LOSS]: 2.5884 [D Acc REAL]: 77.79% [D Acc FAKE]: 19.38% [D Acc REAL - TEST]: 74.12%",
        "[D LOSS]: 0.3484 [G LOSS]: 2.6127 [D Acc REAL]: 78.09% [D Acc FAKE]: 18.95% [D Acc REAL - TEST]: 61.29%",
        "[D LOSS]: 0.3469 [G LOSS]: 2.5993 [D Acc REAL]: 78.18% [D Acc FAKE]: 18.75% [D Acc REAL - TEST]: 63.36%",
        "[D LOSS]: 0.3458 [G LOSS]: 2.5976 [D Acc REAL]: 78.07% [D Acc FAKE]: 18.94% [D Acc REAL - TEST]: 79.59%",
        "[D LOSS]: 0.3498 [G LOSS]: 2.5991 [D Acc REAL]: 77.97% [D Acc FAKE]: 19.04% [D Acc REAL - TEST]: 89.01%",
        "[D LOSS]: 0.3362 [G LOSS]: 2.6258 [D Acc REAL]: 78.60% [D Acc FAKE]: 18.51% [D Acc REAL - TEST]: 35.04%",
        "[D LOSS]: 0.3417 [G LOSS]: 2.6800 [D Acc REAL]: 78.60% [D Acc FAKE]: 18.65% [D Acc REAL - TEST]: 77.04%",
        "[D LOSS]: 0.3428 [G LOSS]: 2.6642 [D Acc REAL]: 78.44% [D Acc FAKE]: 18.64% [D Acc REAL - TEST]: 94.56%",
        "[D LOSS]: 0.3441 [G LOSS]: 2.6578 [D Acc REAL]: 78.44% [D Acc FAKE]: 18.42% [D Acc REAL - TEST]: 85.96%",
        "[D LOSS]: 0.3385 [G LOSS]: 2.6453 [D Acc REAL]: 78.67% [D Acc FAKE]: 18.39% [D Acc REAL - TEST]: 87.83%",
        "[D LOSS]: 0.3405 [G LOSS]: 2.6905 [D Acc REAL]: 78.66% [D Acc FAKE]: 18.34% [D Acc REAL - TEST]: 46.20%",
        "[D LOSS]: 0.3430 [G LOSS]: 2.6511 [D Acc REAL]: 78.37% [D Acc FAKE]: 18.55% [D Acc REAL - TEST]: 68.21%",
        "[D LOSS]: 0.3392 [G LOSS]: 2.6704 [D Acc REAL]: 78.62% [D Acc FAKE]: 18.58% [D Acc REAL - TEST]: 71.53%",
        "[D LOSS]: 0.3413 [G LOSS]: 2.6937 [D Acc REAL]: 78.63% [D Acc FAKE]: 18.42% [D Acc REAL - TEST]: 83.32%",
        "[D LOSS]: 0.3341 [G LOSS]: 2.6734 [D Acc REAL]: 78.87% [D Acc FAKE]: 18.20% [D Acc REAL - TEST]: 66.93%",
        "[D LOSS]: 0.3308 [G LOSS]: 2.7094 [D Acc REAL]: 79.09% [D Acc FAKE]: 18.07% [D Acc REAL - TEST]: 89.67%",
        "[D LOSS]: 0.3428 [G LOSS]: 2.6993 [D Acc REAL]: 78.67% [D Acc FAKE]: 18.16% [D Acc REAL - TEST]: 84.72%",
        "[D LOSS]: 0.3354 [G LOSS]: 2.7090 [D Acc REAL]: 79.00% [D Acc FAKE]: 18.09% [D Acc REAL - TEST]: 49.18%",
        "[D LOSS]: 0.3344 [G LOSS]: 2.7273 [D Acc REAL]: 78.94% [D Acc FAKE]: 18.11% [D Acc REAL - TEST]: 52.79%",
        "[D LOSS]: 0.3316 [G LOSS]: 2.7256 [D Acc REAL]: 79.14% [D Acc FAKE]: 18.03% [D Acc REAL - TEST]: 44.93%",
        "[D LOSS]: 0.3352 [G LOSS]: 2.7336 [D Acc REAL]: 79.02% [D Acc FAKE]: 18.03% [D Acc REAL - TEST]: 72.21%",
        "[D LOSS]: 0.3336 [G LOSS]: 2.7399 [D Acc REAL]: 79.13% [D Acc FAKE]: 17.86% [D Acc REAL - TEST]: 64.25%",
        "[D LOSS]: 0.3312 [G LOSS]: 2.7280 [D Acc REAL]: 79.06% [D Acc FAKE]: 17.77% [D Acc REAL - TEST]: 79.99%",
        "[D LOSS]: 0.3329 [G LOSS]: 2.7615 [D Acc REAL]: 79.11% [D Acc FAKE]: 17.88% [D Acc REAL - TEST]: 73.51%",
        "[D LOSS]: 0.3284 [G LOSS]: 2.7642 [D Acc REAL]: 79.50% [D Acc FAKE]: 17.57% [D Acc REAL - TEST]: 82.43%",
        "[D LOSS]: 0.3252 [G LOSS]: 2.7890 [D Acc REAL]: 79.53% [D Acc FAKE]: 17.60% [D Acc REAL - TEST]: 87.03%",
        "[D LOSS]: 0.3366 [G LOSS]: 2.7899 [D Acc REAL]: 79.29% [D Acc FAKE]: 17.67% [D Acc REAL - TEST]: 45.66%",
        "[D LOSS]: 0.3196 [G LOSS]: 2.7989 [D Acc REAL]: 79.77% [D Acc FAKE]: 17.27% [D Acc REAL - TEST]: 79.57%",
        "[D LOSS]: 0.3311 [G LOSS]: 2.8053 [D Acc REAL]: 79.44% [D Acc FAKE]: 17.71% [D Acc REAL - TEST]: 66.75%",
        "[D LOSS]: 0.3212 [G LOSS]: 2.8365 [D Acc REAL]: 79.83% [D Acc FAKE]: 17.38% [D Acc REAL - TEST]: 76.73%",
        "[D LOSS]: 0.3218 [G LOSS]: 2.7912 [D Acc REAL]: 79.74% [D Acc FAKE]: 17.32% [D Acc REAL - TEST]: 83.36%",
        "[D LOSS]: 0.3169 [G LOSS]: 2.8348 [D Acc REAL]: 79.96% [D Acc FAKE]: 17.14% [D Acc REAL - TEST]: 94.55%",
        "[D LOSS]: 0.3303 [G LOSS]: 2.8250 [D Acc REAL]: 79.58% [D Acc FAKE]: 17.32% [D Acc REAL - TEST]: 89.74%",
        "[D LOSS]: 0.3256 [G LOSS]: 2.8127 [D Acc REAL]: 79.75% [D Acc FAKE]: 17.44% [D Acc REAL - TEST]: 45.11%",
        "[D LOSS]: 0.3133 [G LOSS]: 2.8406 [D Acc REAL]: 80.15% [D Acc FAKE]: 16.79% [D Acc REAL - TEST]: 64.27%",
        "[D LOSS]: 0.3274 [G LOSS]: 2.8840 [D Acc REAL]: 79.84% [D Acc FAKE]: 17.34% [D Acc REAL - TEST]: 54.34%",
        "[D LOSS]: 0.3062 [G LOSS]: 2.8649 [D Acc REAL]: 80.49% [D Acc FAKE]: 16.66% [D Acc REAL - TEST]: 65.36%",
        "[D LOSS]: 0.3306 [G LOSS]: 2.8542 [D Acc REAL]: 79.57% [D Acc FAKE]: 17.46% [D Acc REAL - TEST]: 62.58%",
        "[D LOSS]: 0.3170 [G LOSS]: 2.8736 [D Acc REAL]: 80.24% [D Acc FAKE]: 16.86% [D Acc REAL - TEST]: 46.29%",
        "[D LOSS]: 0.3150 [G LOSS]: 2.8887 [D Acc REAL]: 80.27% [D Acc FAKE]: 16.72% [D Acc REAL - TEST]: 68.37%",
        "[D LOSS]: 0.3200 [G LOSS]: 2.8665 [D Acc REAL]: 80.00% [D Acc FAKE]: 16.96% [D Acc REAL - TEST]: 69.87%",
        "[D LOSS]: 0.3123 [G LOSS]: 2.9042 [D Acc REAL]: 80.44% [D Acc FAKE]: 16.70% [D Acc REAL - TEST]: 36.79%",
        "[D LOSS]: 0.3188 [G LOSS]: 2.9071 [D Acc REAL]: 80.27% [D Acc FAKE]: 16.78% [D Acc REAL - TEST]: 56.64%",
        "[D LOSS]: 0.3062 [G LOSS]: 2.9417 [D Acc REAL]: 80.77% [D Acc FAKE]: 16.51% [D Acc REAL - TEST]: 96.07%",
        "[D LOSS]: 0.3118 [G LOSS]: 2.9631 [D Acc REAL]: 80.56% [D Acc FAKE]: 16.54% [D Acc REAL - TEST]: 80.66%",
        "[D LOSS]: 0.3191 [G LOSS]: 2.9078 [D Acc REAL]: 80.18% [D Acc FAKE]: 16.94% [D Acc REAL - TEST]: 94.11%",
        "[D LOSS]: 0.3204 [G LOSS]: 2.9396 [D Acc REAL]: 80.36% [D Acc FAKE]: 16.70% [D Acc REAL - TEST]: 76.11%",
        "[D LOSS]: 0.3091 [G LOSS]: 2.9109 [D Acc REAL]: 80.49% [D Acc FAKE]: 16.66% [D Acc REAL - TEST]: 66.06%",
        "[D LOSS]: 0.3122 [G LOSS]: 2.9250 [D Acc REAL]: 80.53% [D Acc FAKE]: 16.42% [D Acc REAL - TEST]: 80.78%",
        "[D LOSS]: 0.3012 [G LOSS]: 2.9816 [D Acc REAL]: 80.98% [D Acc FAKE]: 16.22% [D Acc REAL - TEST]: 93.98%",
        "[D LOSS]: 0.3034 [G LOSS]: 3.0338 [D Acc REAL]: 81.17% [D Acc FAKE]: 15.88% [D Acc REAL - TEST]: 88.49%",
        "[D LOSS]: 0.3009 [G LOSS]: 3.0238 [D Acc REAL]: 81.16% [D Acc FAKE]: 16.04% [D Acc REAL - TEST]: 54.65%",
        "[D LOSS]: 0.3050 [G LOSS]: 3.0417 [D Acc REAL]: 81.15% [D Acc FAKE]: 16.16% [D Acc REAL - TEST]: 66.54%",
        "[D LOSS]: 0.3118 [G LOSS]: 3.0508 [D Acc REAL]: 80.87% [D Acc FAKE]: 16.17% [D Acc REAL - TEST]: 82.71%",
        "[D LOSS]: 0.3012 [G LOSS]: 2.9845 [D Acc REAL]: 81.04% [D Acc FAKE]: 15.84% [D Acc REAL - TEST]: 71.11%",
        "[D LOSS]: 0.3056 [G LOSS]: 3.0519 [D Acc REAL]: 81.08% [D Acc FAKE]: 15.96% [D Acc REAL - TEST]: 71.01%",
        "[D LOSS]: 0.3030 [G LOSS]: 3.0165 [D Acc REAL]: 81.01% [D Acc FAKE]: 16.08% [D Acc REAL - TEST]: 76.15%",
        "[D LOSS]: 0.3014 [G LOSS]: 3.0715 [D Acc REAL]: 81.21% [D Acc FAKE]: 15.70% [D Acc REAL - TEST]: 92.49%",
        "[D LOSS]: 0.3004 [G LOSS]: 3.0202 [D Acc REAL]: 81.34% [D Acc FAKE]: 15.85% [D Acc REAL - TEST]: 92.50%",
        "[D LOSS]: 0.3071 [G LOSS]: 3.0521 [D Acc REAL]: 81.10% [D Acc FAKE]: 15.95% [D Acc REAL - TEST]: 62.07%",
        "[D LOSS]: 0.2963 [G LOSS]: 3.0722 [D Acc REAL]: 81.54% [D Acc FAKE]: 15.61% [D Acc REAL - TEST]: 45.18%",
        "[D LOSS]: 0.2958 [G LOSS]: 3.0927 [D Acc REAL]: 81.50% [D Acc FAKE]: 15.85% [D Acc REAL - TEST]: 79.42%",
        "[D LOSS]: 0.2979 [G LOSS]: 3.1558 [D Acc REAL]: 81.61% [D Acc FAKE]: 15.78% [D Acc REAL - TEST]: 61.66%",
        "[D LOSS]: 0.2918 [G LOSS]: 3.1419 [D Acc REAL]: 81.97% [D Acc FAKE]: 15.28% [D Acc REAL - TEST]: 51.73%",
        "[D LOSS]: 0.2931 [G LOSS]: 3.1020 [D Acc REAL]: 81.80% [D Acc FAKE]: 15.42% [D Acc REAL - TEST]: 49.40%",
        "[D LOSS]: 0.2967 [G LOSS]: 3.1438 [D Acc REAL]: 81.70% [D Acc FAKE]: 15.69% [D Acc REAL - TEST]: 90.09%",
        "[D LOSS]: 0.2996 [G LOSS]: 3.0899 [D Acc REAL]: 81.49% [D Acc FAKE]: 15.37% [D Acc REAL - TEST]: 38.64%",
        "[D LOSS]: 0.2907 [G LOSS]: 3.1190 [D Acc REAL]: 81.94% [D Acc FAKE]: 15.01% [D Acc REAL - TEST]: 70.24%",
        "[D LOSS]: 0.2954 [G LOSS]: 3.1813 [D Acc REAL]: 81.78% [D Acc FAKE]: 15.40% [D Acc REAL - TEST]: 77.87%",
        "[D LOSS]: 0.2910 [G LOSS]: 3.1578 [D Acc REAL]: 81.96% [D Acc FAKE]: 15.09% [D Acc REAL - TEST]: 70.89%",
        "[D LOSS]: 0.2881 [G LOSS]: 3.1102 [D Acc REAL]: 81.92% [D Acc FAKE]: 14.99% [D Acc REAL - TEST]: 58.96%",
        "[D LOSS]: 0.2866 [G LOSS]: 3.2054 [D Acc REAL]: 82.19% [D Acc FAKE]: 14.92% [D Acc REAL - TEST]: 83.94%",
        "[D LOSS]: 0.2914 [G LOSS]: 3.2055 [D Acc REAL]: 82.12% [D Acc FAKE]: 14.99% [D Acc REAL - TEST]: 79.30%",
        "[D LOSS]: 0.2909 [G LOSS]: 3.1810 [D Acc REAL]: 81.99% [D Acc FAKE]: 15.14% [D Acc REAL - TEST]: 81.36%",
        "[D LOSS]: 0.2859 [G LOSS]: 3.1923 [D Acc REAL]: 82.23% [D Acc FAKE]: 14.93% [D Acc REAL - TEST]: 70.14%",
        "[D LOSS]: 0.2849 [G LOSS]: 3.2541 [D Acc REAL]: 82.41% [D Acc FAKE]: 14.53% [D Acc REAL - TEST]: 81.11%",
        "[D LOSS]: 0.2891 [G LOSS]: 3.2026 [D Acc REAL]: 82.24% [D Acc FAKE]: 15.07% [D Acc REAL - TEST]: 90.86%",
        "[D LOSS]: 0.2880 [G LOSS]: 3.2514 [D Acc REAL]: 82.31% [D Acc FAKE]: 14.86% [D Acc REAL - TEST]: 93.63%",
        "[D LOSS]: 0.2847 [G LOSS]: 3.2183 [D Acc REAL]: 82.41% [D Acc FAKE]: 14.83% [D Acc REAL - TEST]: 91.09%",
        "[D LOSS]: 0.2866 [G LOSS]: 3.2116 [D Acc REAL]: 82.27% [D Acc FAKE]: 14.96% [D Acc REAL - TEST]: 77.62%",
        "[D LOSS]: 0.2846 [G LOSS]: 3.2725 [D Acc REAL]: 82.52% [D Acc FAKE]: 14.61% [D Acc REAL - TEST]: 79.29%",
        "[D LOSS]: 0.2853 [G LOSS]: 3.2273 [D Acc REAL]: 82.31% [D Acc FAKE]: 14.79% [D Acc REAL - TEST]: 79.16%",
        "[D LOSS]: 0.2818 [G LOSS]: 3.2887 [D Acc REAL]: 82.65% [D Acc FAKE]: 14.33% [D Acc REAL - TEST]: 63.68%",
        "[D LOSS]: 0.2856 [G LOSS]: 3.2566 [D Acc REAL]: 82.35% [D Acc FAKE]: 14.63% [D Acc REAL - TEST]: 73.71%",
        "[D LOSS]: 0.2778 [G LOSS]: 3.2923 [D Acc REAL]: 82.75% [D Acc FAKE]: 14.31% [D Acc REAL - TEST]: 27.02%",
        "[D LOSS]: 0.2769 [G LOSS]: 3.3392 [D Acc REAL]: 82.92% [D Acc FAKE]: 13.96% [D Acc REAL - TEST]: 18.64%",
        "[D LOSS]: 0.2774 [G LOSS]: 3.3049 [D Acc REAL]: 82.78% [D Acc FAKE]: 14.19% [D Acc REAL - TEST]: 84.75%",
        "[D LOSS]: 0.2847 [G LOSS]: 3.3231 [D Acc REAL]: 82.72% [D Acc FAKE]: 14.23% [D Acc REAL - TEST]: 72.22%",
        "[D LOSS]: 0.2797 [G LOSS]: 3.2807 [D Acc REAL]: 82.72% [D Acc FAKE]: 14.30% [D Acc REAL - TEST]: 54.93%",
        "[D LOSS]: 0.2816 [G LOSS]: 3.3232 [D Acc REAL]: 82.73% [D Acc FAKE]: 14.36% [D Acc REAL - TEST]: 73.48%",
        "[D LOSS]: 0.2657 [G LOSS]: 3.3294 [D Acc REAL]: 83.29% [D Acc FAKE]: 13.65% [D Acc REAL - TEST]: 96.44%",
        "[D LOSS]: 0.2815 [G LOSS]: 3.3101 [D Acc REAL]: 82.91% [D Acc FAKE]: 14.03% [D Acc REAL - TEST]: 88.36%",
        "[D LOSS]: 0.2751 [G LOSS]: 3.3645 [D Acc REAL]: 83.07% [D Acc FAKE]: 14.14% [D Acc REAL - TEST]: 70.72%",
        "[D LOSS]: 0.2721 [G LOSS]: 3.3525 [D Acc REAL]: 83.12% [D Acc FAKE]: 14.07% [D Acc REAL - TEST]: 74.34%",
        "[D LOSS]: 0.2858 [G LOSS]: 3.3351 [D Acc REAL]: 82.73% [D Acc FAKE]: 14.41% [D Acc REAL - TEST]: 54.66%",
        "[D LOSS]: 0.2751 [G LOSS]: 3.3276 [D Acc REAL]: 83.02% [D Acc FAKE]: 14.05% [D Acc REAL - TEST]: 85.13%",
        "[D LOSS]: 0.2620 [G LOSS]: 3.4118 [D Acc REAL]: 83.63% [D Acc FAKE]: 13.57% [D Acc REAL - TEST]: 76.25%",
        "[D LOSS]: 0.2771 [G LOSS]: 3.3336 [D Acc REAL]: 83.29% [D Acc FAKE]: 14.06% [D Acc REAL - TEST]: 50.71%",
        "[D LOSS]: 0.2783 [G LOSS]: 3.3744 [D Acc REAL]: 82.90% [D Acc FAKE]: 14.09% [D Acc REAL - TEST]: 56.79%",
        "[D LOSS]: 0.2706 [G LOSS]: 3.3603 [D Acc REAL]: 83.38% [D Acc FAKE]: 13.63% [D Acc REAL - TEST]: 70.46%",
        "[D LOSS]: 0.2753 [G LOSS]: 3.4120 [D Acc REAL]: 83.22% [D Acc FAKE]: 13.86% [D Acc REAL - TEST]: 79.64%",
        "[D LOSS]: 0.2647 [G LOSS]: 3.3996 [D Acc REAL]: 83.71% [D Acc FAKE]: 13.26% [D Acc REAL - TEST]: 85.06%",
        "[D LOSS]: 0.2734 [G LOSS]: 3.4332 [D Acc REAL]: 83.44% [D Acc FAKE]: 13.79% [D Acc REAL - TEST]: 53.54%",
        "[D LOSS]: 0.2765 [G LOSS]: 3.3854 [D Acc REAL]: 83.06% [D Acc FAKE]: 13.86% [D Acc REAL - TEST]: 81.23%",
        "[D LOSS]: 0.2605 [G LOSS]: 3.4553 [D Acc REAL]: 83.91% [D Acc FAKE]: 13.45% [D Acc REAL - TEST]: 50.31%",
        "[D LOSS]: 0.2654 [G LOSS]: 3.4503 [D Acc REAL]: 83.85% [D Acc FAKE]: 13.41% [D Acc REAL - TEST]: 71.58%",
        "[D LOSS]: 0.2797 [G LOSS]: 3.4109 [D Acc REAL]: 83.12% [D Acc FAKE]: 13.86% [D Acc REAL - TEST]: 71.98%",
        "[D LOSS]: 0.2551 [G LOSS]: 3.4130 [D Acc REAL]: 84.07% [D Acc FAKE]: 13.02% [D Acc REAL - TEST]: 62.59%",
        "[D LOSS]: 0.2712 [G LOSS]: 3.4804 [D Acc REAL]: 83.51% [D Acc FAKE]: 13.53% [D Acc REAL - TEST]: 72.43%",
        "[D LOSS]: 0.2545 [G LOSS]: 3.5182 [D Acc REAL]: 84.15% [D Acc FAKE]: 12.92% [D Acc REAL - TEST]: 87.79%",
        "[D LOSS]: 0.2643 [G LOSS]: 3.5130 [D Acc REAL]: 83.70% [D Acc FAKE]: 13.42% [D Acc REAL - TEST]: 92.41%",
        "[D LOSS]: 0.2734 [G LOSS]: 3.4784 [D Acc REAL]: 83.56% [D Acc FAKE]: 13.55% [D Acc REAL - TEST]: 79.66%",
        "[D LOSS]: 0.2507 [G LOSS]: 3.5041 [D Acc REAL]: 84.28% [D Acc FAKE]: 12.70% [D Acc REAL - TEST]: 76.47%",
        "[D LOSS]: 0.2676 [G LOSS]: 3.6072 [D Acc REAL]: 83.94% [D Acc FAKE]: 12.97% [D Acc REAL - TEST]: 75.57%",
        "[D LOSS]: 0.2561 [G LOSS]: 3.5438 [D Acc REAL]: 84.23% [D Acc FAKE]: 12.87% [D Acc REAL - TEST]: 78.31%",
        "[D LOSS]: 0.2515 [G LOSS]: 3.5651 [D Acc REAL]: 84.43% [D Acc FAKE]: 12.79% [D Acc REAL - TEST]: 75.78%",
        "[D LOSS]: 0.2625 [G LOSS]: 3.5548 [D Acc REAL]: 84.17% [D Acc FAKE]: 12.86% [D Acc REAL - TEST]: 92.35%",
        "[D LOSS]: 0.2655 [G LOSS]: 3.6054 [D Acc REAL]: 83.97% [D Acc FAKE]: 13.18% [D Acc REAL - TEST]: 85.02%",
        "[D LOSS]: 0.2497 [G LOSS]: 3.5881 [D Acc REAL]: 84.55% [D Acc FAKE]: 12.60% [D Acc REAL - TEST]: 69.34%",
        "[D LOSS]: 0.2589 [G LOSS]: 3.5816 [D Acc REAL]: 84.12% [D Acc FAKE]: 13.18% [D Acc REAL - TEST]: 93.76%",
        "[D LOSS]: 0.2600 [G LOSS]: 3.5991 [D Acc REAL]: 84.39% [D Acc FAKE]: 12.81% [D Acc REAL - TEST]: 42.97%",
        "[D LOSS]: 0.2598 [G LOSS]: 3.5728 [D Acc REAL]: 84.16% [D Acc FAKE]: 12.83% [D Acc REAL - TEST]: 78.43%",
        "[D LOSS]: 0.2600 [G LOSS]: 3.5705 [D Acc REAL]: 84.27% [D Acc FAKE]: 12.97% [D Acc REAL - TEST]: 79.90%",
        "[D LOSS]: 0.2435 [G LOSS]: 3.5773 [D Acc REAL]: 84.73% [D Acc FAKE]: 12.43% [D Acc REAL - TEST]: 33.97%",
        "[D LOSS]: 0.2501 [G LOSS]: 3.6322 [D Acc REAL]: 84.78% [D Acc FAKE]: 12.47% [D Acc REAL - TEST]: 89.75%",
        "[D LOSS]: 0.2792 [G LOSS]: 3.5702 [D Acc REAL]: 83.58% [D Acc FAKE]: 13.36% [D Acc REAL - TEST]: 61.48%",
        "[D LOSS]: 0.2470 [G LOSS]: 3.5482 [D Acc REAL]: 84.64% [D Acc FAKE]: 12.63% [D Acc REAL - TEST]: 85.87%",
        "[D LOSS]: 0.2573 [G LOSS]: 3.6531 [D Acc REAL]: 84.49% [D Acc FAKE]: 12.59% [D Acc REAL - TEST]: 61.24%",
        "[D LOSS]: 0.2450 [G LOSS]: 3.6723 [D Acc REAL]: 84.97% [D Acc FAKE]: 12.42% [D Acc REAL - TEST]: 93.55%",
        "[D LOSS]: 0.2495 [G LOSS]: 3.6502 [D Acc REAL]: 84.81% [D Acc FAKE]: 12.26% [D Acc REAL - TEST]: 89.69%",
        "[D LOSS]: 0.2471 [G LOSS]: 3.6628 [D Acc REAL]: 84.76% [D Acc FAKE]: 12.37% [D Acc REAL - TEST]: 91.43%",
        "[D LOSS]: 0.2602 [G LOSS]: 3.6274 [D Acc REAL]: 84.40% [D Acc FAKE]: 12.51% [D Acc REAL - TEST]: 84.83%",
        "[D LOSS]: 0.2419 [G LOSS]: 3.6778 [D Acc REAL]: 85.03% [D Acc FAKE]: 12.45% [D Acc REAL - TEST]: 64.12%",
        "[D LOSS]: 0.2499 [G LOSS]: 3.7086 [D Acc REAL]: 84.88% [D Acc FAKE]: 12.15% [D Acc REAL - TEST]: 74.48%",
        "[D LOSS]: 0.2541 [G LOSS]: 3.7135 [D Acc REAL]: 84.82% [D Acc FAKE]: 12.39% [D Acc REAL - TEST]: 65.58%",
        "[D LOSS]: 0.2434 [G LOSS]: 3.7125 [D Acc REAL]: 85.27% [D Acc FAKE]: 12.01% [D Acc REAL - TEST]: 87.83%",
        "[D LOSS]: 0.2487 [G LOSS]: 3.6684 [D Acc REAL]: 84.84% [D Acc FAKE]: 12.40% [D Acc REAL - TEST]: 81.54%",
        "[D LOSS]: 0.2426 [G LOSS]: 3.6974 [D Acc REAL]: 85.37% [D Acc FAKE]: 12.18% [D Acc REAL - TEST]: 48.46%",
        "[D LOSS]: 0.2356 [G LOSS]: 3.7831 [D Acc REAL]: 85.39% [D Acc FAKE]: 11.91% [D Acc REAL - TEST]: 93.30%",
        "[D LOSS]: 0.2580 [G LOSS]: 3.7615 [D Acc REAL]: 84.77% [D Acc FAKE]: 12.21% [D Acc REAL - TEST]: 94.79%",
        "[D LOSS]: 0.2394 [G LOSS]: 3.7473 [D Acc REAL]: 85.31% [D Acc FAKE]: 11.72% [D Acc REAL - TEST]: 68.37%",
        "[D LOSS]: 0.2400 [G LOSS]: 3.7562 [D Acc REAL]: 85.31% [D Acc FAKE]: 12.01% [D Acc REAL - TEST]: 86.41%",
        "[D LOSS]: 0.2540 [G LOSS]: 3.7915 [D Acc REAL]: 84.92% [D Acc FAKE]: 12.20% [D Acc REAL - TEST]: 81.45%",
        "[D LOSS]: 0.2362 [G LOSS]: 3.7783 [D Acc REAL]: 85.56% [D Acc FAKE]: 11.72% [D Acc REAL - TEST]: 97.17%",
        "[D LOSS]: 0.2606 [G LOSS]: 3.6791 [D Acc REAL]: 84.44% [D Acc FAKE]: 12.44% [D Acc REAL - TEST]: 65.68%",
        "[D LOSS]: 0.2381 [G LOSS]: 3.7529 [D Acc REAL]: 85.49% [D Acc FAKE]: 11.77% [D Acc REAL - TEST]: 12.40%",
        "[D LOSS]: 0.2401 [G LOSS]: 3.7205 [D Acc REAL]: 85.30% [D Acc FAKE]: 11.69% [D Acc REAL - TEST]: 73.22%",
        "[D LOSS]: 0.2389 [G LOSS]: 3.7942 [D Acc REAL]: 85.42% [D Acc FAKE]: 11.58% [D Acc REAL - TEST]: 68.62%",
        "[D LOSS]: 0.2515 [G LOSS]: 3.7661 [D Acc REAL]: 85.02% [D Acc FAKE]: 12.11% [D Acc REAL - TEST]: 93.01%",
        "[D LOSS]: 0.2295 [G LOSS]: 3.7775 [D Acc REAL]: 85.67% [D Acc FAKE]: 11.43% [D Acc REAL - TEST]: 86.07%",
        "[D LOSS]: 0.2449 [G LOSS]: 3.8396 [D Acc REAL]: 85.28% [D Acc FAKE]: 11.80% [D Acc REAL - TEST]: 86.23%",
        "[D LOSS]: 0.2374 [G LOSS]: 3.8269 [D Acc REAL]: 85.63% [D Acc FAKE]: 11.51% [D Acc REAL - TEST]: 87.61%",
        "[D LOSS]: 0.2436 [G LOSS]: 3.8068 [D Acc REAL]: 85.37% [D Acc FAKE]: 11.88% [D Acc REAL - TEST]: 92.09%",
        "[D LOSS]: 0.2330 [G LOSS]: 3.8814 [D Acc REAL]: 85.81% [D Acc FAKE]: 11.75% [D Acc REAL - TEST]: 45.53%",
        "[D LOSS]: 0.2340 [G LOSS]: 3.8587 [D Acc REAL]: 85.77% [D Acc FAKE]: 11.45% [D Acc REAL - TEST]: 49.59%",
        "[D LOSS]: 0.2354 [G LOSS]: 3.8313 [D Acc REAL]: 85.66% [D Acc FAKE]: 11.50% [D Acc REAL - TEST]: 85.88%",
        "[D LOSS]: 0.2375 [G LOSS]: 3.8958 [D Acc REAL]: 85.47% [D Acc FAKE]: 11.83% [D Acc REAL - TEST]: 89.42%",
        "[D LOSS]: 0.2276 [G LOSS]: 3.9768 [D Acc REAL]: 86.19% [D Acc FAKE]: 11.11% [D Acc REAL - TEST]: 80.87%",
        "[D LOSS]: 0.2381 [G LOSS]: 3.9067 [D Acc REAL]: 85.85% [D Acc FAKE]: 11.07% [D Acc REAL - TEST]: 61.24%",
        "[D LOSS]: 0.2423 [G LOSS]: 3.8543 [D Acc REAL]: 85.35% [D Acc FAKE]: 11.69% [D Acc REAL - TEST]: 78.06%",
        "[D LOSS]: 0.2229 [G LOSS]: 3.9195 [D Acc REAL]: 86.29% [D Acc FAKE]: 10.85% [D Acc REAL - TEST]: 62.68%",
        "[D LOSS]: 0.2400 [G LOSS]: 3.9534 [D Acc REAL]: 85.82% [D Acc FAKE]: 11.47% [D Acc REAL - TEST]: 72.68%",
        "[D LOSS]: 0.2253 [G LOSS]: 3.8943 [D Acc REAL]: 86.12% [D Acc FAKE]: 11.34% [D Acc REAL - TEST]: 95.61%",
        "[D LOSS]: 0.2594 [G LOSS]: 3.9043 [D Acc REAL]: 85.17% [D Acc FAKE]: 11.74% [D Acc REAL - TEST]: 62.97%",
        "[D LOSS]: 0.2146 [G LOSS]: 3.8848 [D Acc REAL]: 86.52% [D Acc FAKE]: 10.92% [D Acc REAL - TEST]: 86.52%",
        "[D LOSS]: 0.2280 [G LOSS]: 3.9096 [D Acc REAL]: 86.09% [D Acc FAKE]: 11.11% [D Acc REAL - TEST]: 69.98%",
        "[D LOSS]: 0.2373 [G LOSS]: 3.9387 [D Acc REAL]: 85.83% [D Acc FAKE]: 11.39% [D Acc REAL - TEST]: 74.38%",
        "[D LOSS]: 0.2341 [G LOSS]: 3.8988 [D Acc REAL]: 85.71% [D Acc FAKE]: 11.51% [D Acc REAL - TEST]: 86.86%",
        "[D LOSS]: 0.2203 [G LOSS]: 3.9718 [D Acc REAL]: 86.37% [D Acc FAKE]: 10.69% [D Acc REAL - TEST]: 51.51%",
        "[D LOSS]: 0.2268 [G LOSS]: 3.9994 [D Acc REAL]: 86.17% [D Acc FAKE]: 11.11% [D Acc REAL - TEST]: 96.04%",
        "[D LOSS]: 0.2264 [G LOSS]: 4.0142 [D Acc REAL]: 86.51% [D Acc FAKE]: 10.75% [D Acc REAL - TEST]: 67.92%",
        "[D LOSS]: 0.2361 [G LOSS]: 4.0659 [D Acc REAL]: 86.17% [D Acc FAKE]: 11.24% [D Acc REAL - TEST]: 51.20%",
        "[D LOSS]: 0.2331 [G LOSS]: 4.0144 [D Acc REAL]: 85.98% [D Acc FAKE]: 11.14% [D Acc REAL - TEST]: 70.39%",
        "[D LOSS]: 0.2244 [G LOSS]: 3.9503 [D Acc REAL]: 86.34% [D Acc FAKE]: 10.85% [D Acc REAL - TEST]: 93.73%",
        "[D LOSS]: 0.2197 [G LOSS]: 3.9723 [D Acc REAL]: 86.60% [D Acc FAKE]: 10.46% [D Acc REAL - TEST]: 80.25%",
        "[D LOSS]: 0.2388 [G LOSS]: 3.9953 [D Acc REAL]: 85.87% [D Acc FAKE]: 11.10% [D Acc REAL - TEST]: 62.51%",
        "[D LOSS]: 0.2221 [G LOSS]: 3.9966 [D Acc REAL]: 86.42% [D Acc FAKE]: 10.66% [D Acc REAL - TEST]: 98.17%",
        "[D LOSS]: 0.2312 [G LOSS]: 4.0496 [D Acc REAL]: 86.42% [D Acc FAKE]: 10.88% [D Acc REAL - TEST]: 54.40%",
        "[D LOSS]: 0.2211 [G LOSS]: 4.0199 [D Acc REAL]: 86.56% [D Acc FAKE]: 10.63% [D Acc REAL - TEST]: 81.03%",
        "[D LOSS]: 0.2235 [G LOSS]: 3.9962 [D Acc REAL]: 86.48% [D Acc FAKE]: 10.79% [D Acc REAL - TEST]: 79.77%",
        "[D LOSS]: 0.2190 [G LOSS]: 4.1044 [D Acc REAL]: 86.65% [D Acc FAKE]: 10.49% [D Acc REAL - TEST]: 88.36%",
        "[D LOSS]: 0.2367 [G LOSS]: 4.0741 [D Acc REAL]: 86.24% [D Acc FAKE]: 10.85% [D Acc REAL - TEST]: 83.81%",
        "[D LOSS]: 0.2157 [G LOSS]: 4.0238 [D Acc REAL]: 86.83% [D Acc FAKE]: 10.38% [D Acc REAL - TEST]: 72.11%",
        "[D LOSS]: 0.2174 [G LOSS]: 4.0658 [D Acc REAL]: 86.81% [D Acc FAKE]: 10.62% [D Acc REAL - TEST]: 80.37%",
        "[D LOSS]: 0.2332 [G LOSS]: 4.0387 [D Acc REAL]: 86.26% [D Acc FAKE]: 10.88% [D Acc REAL - TEST]: 72.37%",
        "[D LOSS]: 0.2262 [G LOSS]: 4.0527 [D Acc REAL]: 86.35% [D Acc FAKE]: 11.04% [D Acc REAL - TEST]: 84.38%",
        "[D LOSS]: 0.2168 [G LOSS]: 4.1456 [D Acc REAL]: 87.20% [D Acc FAKE]: 10.16% [D Acc REAL - TEST]: 79.85%",
        "[D LOSS]: 0.2195 [G LOSS]: 4.0276 [D Acc REAL]: 86.75% [D Acc FAKE]: 10.48% [D Acc REAL - TEST]: 76.76%",
        "[D LOSS]: 0.2364 [G LOSS]: 4.0362 [D Acc REAL]: 86.24% [D Acc FAKE]: 11.02% [D Acc REAL - TEST]: 61.37%",
        "[D LOSS]: 0.2153 [G LOSS]: 4.1387 [D Acc REAL]: 87.13% [D Acc FAKE]: 10.13% [D Acc REAL - TEST]: 85.53%",
        "[D LOSS]: 0.2164 [G LOSS]: 4.1088 [D Acc REAL]: 87.01% [D Acc FAKE]: 10.16% [D Acc REAL - TEST]: 63.95%",
        "[D LOSS]: 0.2102 [G LOSS]: 4.1387 [D Acc REAL]: 87.07% [D Acc FAKE]: 10.01% [D Acc REAL - TEST]: 71.78%",
        "[D LOSS]: 0.2227 [G LOSS]: 4.1048 [D Acc REAL]: 86.78% [D Acc FAKE]: 10.28% [D Acc REAL - TEST]: 75.86%",
        "[D LOSS]: 0.2036 [G LOSS]: 4.1342 [D Acc REAL]: 87.45% [D Acc FAKE]: 9.73% [D Acc REAL - TEST]: 67.29%",
        "[D LOSS]: 0.2192 [G LOSS]: 4.2118 [D Acc REAL]: 87.09% [D Acc FAKE]: 10.09% [D Acc REAL - TEST]: 91.58%",
        "[D LOSS]: 0.2170 [G LOSS]: 4.1095 [D Acc REAL]: 87.38% [D Acc FAKE]: 9.87% [D Acc REAL - TEST]: 70.95%",
        "[D LOSS]: 0.2172 [G LOSS]: 4.1681 [D Acc REAL]: 87.11% [D Acc FAKE]: 10.08% [D Acc REAL - TEST]: 47.26%",
        "[D LOSS]: 0.2201 [G LOSS]: 4.1996 [D Acc REAL]: 87.03% [D Acc FAKE]: 10.27% [D Acc REAL - TEST]: 81.05%",
        "[D LOSS]: 0.2120 [G LOSS]: 4.1783 [D Acc REAL]: 87.21% [D Acc FAKE]: 10.01% [D Acc REAL - TEST]: 85.21%",
        "[D LOSS]: 0.2239 [G LOSS]: 4.1128 [D Acc REAL]: 86.78% [D Acc FAKE]: 10.53% [D Acc REAL - TEST]: 81.86%",
        "[D LOSS]: 0.2149 [G LOSS]: 4.1431 [D Acc REAL]: 87.22% [D Acc FAKE]: 10.04% [D Acc REAL - TEST]: 45.79%",
        "[D LOSS]: 0.2146 [G LOSS]: 4.1453 [D Acc REAL]: 87.12% [D Acc FAKE]: 9.96% [D Acc REAL - TEST]: 81.71%",
        "[D LOSS]: 0.2202 [G LOSS]: 4.2116 [D Acc REAL]: 86.97% [D Acc FAKE]: 10.52% [D Acc REAL - TEST]: 51.81%",
        "[D LOSS]: 0.2177 [G LOSS]: 4.2394 [D Acc REAL]: 87.22% [D Acc FAKE]: 10.06% [D Acc REAL - TEST]: 52.50%",
        "[D LOSS]: 0.2031 [G LOSS]: 4.1431 [D Acc REAL]: 87.51% [D Acc FAKE]: 9.56% [D Acc REAL - TEST]: 73.66%",
        "[D LOSS]: 0.2216 [G LOSS]: 4.2223 [D Acc REAL]: 87.06% [D Acc FAKE]: 9.92% [D Acc REAL - TEST]: 91.83%",
        "[D LOSS]: 0.2241 [G LOSS]: 4.1691 [D Acc REAL]: 86.96% [D Acc FAKE]: 10.50% [D Acc REAL - TEST]: 31.66%",
        "[D LOSS]: 0.2116 [G LOSS]: 4.1811 [D Acc REAL]: 87.45% [D Acc FAKE]: 9.78% [D Acc REAL - TEST]: 75.85%",
        "[D LOSS]: 0.2088 [G LOSS]: 4.1723 [D Acc REAL]: 87.29% [D Acc FAKE]: 10.07% [D Acc REAL - TEST]: 98.19%",
        "[D LOSS]: 0.2142 [G LOSS]: 4.1602 [D Acc REAL]: 87.17% [D Acc FAKE]: 10.02% [D Acc REAL - TEST]: 84.74%",
        "[D LOSS]: 0.2004 [G LOSS]: 4.2313 [D Acc REAL]: 87.84% [D Acc FAKE]: 9.67% [D Acc REAL - TEST]: 82.07%",
        "[D LOSS]: 0.2078 [G LOSS]: 4.2684 [D Acc REAL]: 87.47% [D Acc FAKE]: 10.00% [D Acc REAL - TEST]: 88.00%",
        "[D LOSS]: 0.2199 [G LOSS]: 4.2441 [D Acc REAL]: 87.15% [D Acc FAKE]: 10.23% [D Acc REAL - TEST]: 27.43%",
        "[D LOSS]: 0.2066 [G LOSS]: 4.2645 [D Acc REAL]: 87.43% [D Acc FAKE]: 9.85% [D Acc REAL - TEST]: 54.80%",
        "[D LOSS]: 0.2159 [G LOSS]: 4.2810 [D Acc REAL]: 87.13% [D Acc FAKE]: 10.06% [D Acc REAL - TEST]: 83.25%",
        "[D LOSS]: 0.2111 [G LOSS]: 4.1904 [D Acc REAL]: 87.32% [D Acc FAKE]: 9.84% [D Acc REAL - TEST]: 68.51%",
        "[D LOSS]: 0.2040 [G LOSS]: 4.3521 [D Acc REAL]: 87.73% [D Acc FAKE]: 9.77% [D Acc REAL - TEST]: 60.88%",
        "[D LOSS]: 0.1988 [G LOSS]: 4.2963 [D Acc REAL]: 88.05% [D Acc FAKE]: 9.18% [D Acc REAL - TEST]: 42.51%",
        "[D LOSS]: 0.2160 [G LOSS]: 4.3605 [D Acc REAL]: 87.31% [D Acc FAKE]: 10.23% [D Acc REAL - TEST]: 98.82%",
        "[D LOSS]: 0.2055 [G LOSS]: 4.2753 [D Acc REAL]: 87.71% [D Acc FAKE]: 9.66% [D Acc REAL - TEST]: 84.48%",
        "[D LOSS]: 0.2040 [G LOSS]: 4.3241 [D Acc REAL]: 87.86% [D Acc FAKE]: 9.46% [D Acc REAL - TEST]: 95.55%",
        "[D LOSS]: 0.2014 [G LOSS]: 4.3677 [D Acc REAL]: 87.85% [D Acc FAKE]: 9.51% [D Acc REAL - TEST]: 86.68%",
        "[D LOSS]: 0.2167 [G LOSS]: 4.4685 [D Acc REAL]: 87.64% [D Acc FAKE]: 9.59% [D Acc REAL - TEST]: 74.28%",
        "[D LOSS]: 0.1933 [G LOSS]: 4.3568 [D Acc REAL]: 88.19% [D Acc FAKE]: 9.15% [D Acc REAL - TEST]: 87.65%",
        "[D LOSS]: 0.1982 [G LOSS]: 4.3224 [D Acc REAL]: 88.05% [D Acc FAKE]: 9.48% [D Acc REAL - TEST]: 70.76%",
        "[D LOSS]: 0.2126 [G LOSS]: 4.3396 [D Acc REAL]: 87.46% [D Acc FAKE]: 9.78% [D Acc REAL - TEST]: 80.43%",
        "[D LOSS]: 0.2085 [G LOSS]: 4.3845 [D Acc REAL]: 87.86% [D Acc FAKE]: 9.38% [D Acc REAL - TEST]: 83.71%",
        "[D LOSS]: 0.2054 [G LOSS]: 4.3189 [D Acc REAL]: 87.72% [D Acc FAKE]: 9.61% [D Acc REAL - TEST]: 81.48%",
        "[D LOSS]: 0.1925 [G LOSS]: 4.4019 [D Acc REAL]: 88.27% [D Acc FAKE]: 9.09% [D Acc REAL - TEST]: 81.30%",
        "[D LOSS]: 0.2097 [G LOSS]: 4.4539 [D Acc REAL]: 87.82% [D Acc FAKE]: 9.35% [D Acc REAL - TEST]: 58.47%",
        "[D LOSS]: 0.1938 [G LOSS]: 4.3425 [D Acc REAL]: 88.26% [D Acc FAKE]: 8.95% [D Acc REAL - TEST]: 84.07%",
        "[D LOSS]: 0.2090 [G LOSS]: 4.3944 [D Acc REAL]: 87.90% [D Acc FAKE]: 9.46% [D Acc REAL - TEST]: 54.73%",
        "[D LOSS]: 0.1996 [G LOSS]: 4.4000 [D Acc REAL]: 88.24% [D Acc FAKE]: 9.23% [D Acc REAL - TEST]: 89.27%",
        "[D LOSS]: 0.1930 [G LOSS]: 4.3892 [D Acc REAL]: 88.30% [D Acc FAKE]: 8.98% [D Acc REAL - TEST]: 83.10%",
        "[D LOSS]: 0.2099 [G LOSS]: 4.3202 [D Acc REAL]: 87.63% [D Acc FAKE]: 9.61% [D Acc REAL - TEST]: 78.05%",
        "[D LOSS]: 0.2092 [G LOSS]: 4.4004 [D Acc REAL]: 87.74% [D Acc FAKE]: 9.62% [D Acc REAL - TEST]: 84.52%",
        "[D LOSS]: 0.2045 [G LOSS]: 4.4068 [D Acc REAL]: 87.91% [D Acc FAKE]: 9.52% [D Acc REAL - TEST]: 76.53%",
        "[D LOSS]: 0.1918 [G LOSS]: 4.4239 [D Acc REAL]: 88.43% [D Acc FAKE]: 9.06% [D Acc REAL - TEST]: 70.72%",
        "[D LOSS]: 0.2150 [G LOSS]: 4.3735 [D Acc REAL]: 88.17% [D Acc FAKE]: 9.19% [D Acc REAL - TEST]: 65.23%",
        "[D LOSS]: 0.1761 [G LOSS]: 4.3987 [D Acc REAL]: 88.85% [D Acc FAKE]: 8.59% [D Acc REAL - TEST]: 71.77%",
        "[D LOSS]: 0.2108 [G LOSS]: 4.3955 [D Acc REAL]: 87.61% [D Acc FAKE]: 10.01% [D Acc REAL - TEST]: 94.08%",
        "[D LOSS]: 0.2128 [G LOSS]: 4.3831 [D Acc REAL]: 87.54% [D Acc FAKE]: 9.67% [D Acc REAL - TEST]: 94.98%",
        "[D LOSS]: 0.2000 [G LOSS]: 4.4478 [D Acc REAL]: 88.03% [D Acc FAKE]: 9.47% [D Acc REAL - TEST]: 65.17%",
        "[D LOSS]: 0.1885 [G LOSS]: 4.4318 [D Acc REAL]: 88.31% [D Acc FAKE]: 8.95% [D Acc REAL - TEST]: 86.35%",
        "[D LOSS]: 0.1996 [G LOSS]: 4.5199 [D Acc REAL]: 88.16% [D Acc FAKE]: 9.37% [D Acc REAL - TEST]: 91.88%",
        "[D LOSS]: 0.1963 [G LOSS]: 4.5049 [D Acc REAL]: 88.27% [D Acc FAKE]: 9.13% [D Acc REAL - TEST]: 74.49%",
        "[D LOSS]: 0.2081 [G LOSS]: 4.4055 [D Acc REAL]: 88.01% [D Acc FAKE]: 9.27% [D Acc REAL - TEST]: 69.97%",
        "[D LOSS]: 0.2019 [G LOSS]: 4.5004 [D Acc REAL]: 88.15% [D Acc FAKE]: 9.35% [D Acc REAL - TEST]: 88.89%",
        "[D LOSS]: 0.1825 [G LOSS]: 4.4416 [D Acc REAL]: 88.79% [D Acc FAKE]: 8.45% [D Acc REAL - TEST]: 81.05%",
        "[D LOSS]: 0.1906 [G LOSS]: 4.5683 [D Acc REAL]: 88.57% [D Acc FAKE]: 8.90% [D Acc REAL - TEST]: 69.99%",
        "[D LOSS]: 0.1956 [G LOSS]: 4.5558 [D Acc REAL]: 88.58% [D Acc FAKE]: 9.06% [D Acc REAL - TEST]: 71.84%",
        "[D LOSS]: 0.2054 [G LOSS]: 4.4579 [D Acc REAL]: 87.86% [D Acc FAKE]: 9.50% [D Acc REAL - TEST]: 96.42%",
        "[D LOSS]: 0.1790 [G LOSS]: 4.6116 [D Acc REAL]: 89.10% [D Acc FAKE]: 8.24% [D Acc REAL - TEST]: 91.69%",
        "[D LOSS]: 0.1950 [G LOSS]: 4.6370 [D Acc REAL]: 88.61% [D Acc FAKE]: 9.01% [D Acc REAL - TEST]: 51.50%",
        "[D LOSS]: 0.1887 [G LOSS]: 4.4930 [D Acc REAL]: 88.63% [D Acc FAKE]: 8.95% [D Acc REAL - TEST]: 79.40%",
        "[D LOSS]: 0.1795 [G LOSS]: 4.6661 [D Acc REAL]: 89.44% [D Acc FAKE]: 8.15% [D Acc REAL - TEST]: 48.43%",
        "[D LOSS]: 0.1919 [G LOSS]: 4.6695 [D Acc REAL]: 88.71% [D Acc FAKE]: 8.81% [D Acc REAL - TEST]: 63.50%",
        "[D LOSS]: 0.1826 [G LOSS]: 4.6469 [D Acc REAL]: 89.03% [D Acc FAKE]: 8.51% [D Acc REAL - TEST]: 73.33%",
        "[D LOSS]: 0.2014 [G LOSS]: 4.5455 [D Acc REAL]: 88.20% [D Acc FAKE]: 9.31% [D Acc REAL - TEST]: 83.86%",
        "[D LOSS]: 0.1860 [G LOSS]: 4.7109 [D Acc REAL]: 89.02% [D Acc FAKE]: 8.52% [D Acc REAL - TEST]: 53.69%",
        "[D LOSS]: 0.1939 [G LOSS]: 4.6141 [D Acc REAL]: 88.67% [D Acc FAKE]: 9.04% [D Acc REAL - TEST]: 61.97%",
        "[D LOSS]: 0.1753 [G LOSS]: 4.6937 [D Acc REAL]: 89.42% [D Acc FAKE]: 8.11% [D Acc REAL - TEST]: 85.35%",
        "[D LOSS]: 0.2015 [G LOSS]: 4.6247 [D Acc REAL]: 88.46% [D Acc FAKE]: 8.70% [D Acc REAL - TEST]: 70.21%",
        "[D LOSS]: 0.1721 [G LOSS]: 4.6282 [D Acc REAL]: 89.36% [D Acc FAKE]: 8.14% [D Acc REAL - TEST]: 52.27%",
        "[D LOSS]: 0.1932 [G LOSS]: 4.6546 [D Acc REAL]: 88.52% [D Acc FAKE]: 8.76% [D Acc REAL - TEST]: 85.79%",
        "[D LOSS]: 0.1953 [G LOSS]: 4.7296 [D Acc REAL]: 88.71% [D Acc FAKE]: 8.70% [D Acc REAL - TEST]: 81.70%",
        "[D LOSS]: 0.1915 [G LOSS]: 4.6098 [D Acc REAL]: 88.91% [D Acc FAKE]: 8.53% [D Acc REAL - TEST]: 59.51%",
        "[D LOSS]: 0.1865 [G LOSS]: 4.5545 [D Acc REAL]: 88.95% [D Acc FAKE]: 8.56% [D Acc REAL - TEST]: 78.33%",
        "[D LOSS]: 0.1954 [G LOSS]: 4.6667 [D Acc REAL]: 88.81% [D Acc FAKE]: 8.56% [D Acc REAL - TEST]: 89.50%",
        "[D LOSS]: 0.1762 [G LOSS]: 4.6107 [D Acc REAL]: 89.12% [D Acc FAKE]: 8.27% [D Acc REAL - TEST]: 60.89%",
        "[D LOSS]: 0.2095 [G LOSS]: 4.5827 [D Acc REAL]: 88.16% [D Acc FAKE]: 9.30% [D Acc REAL - TEST]: 73.04%",
        "[D LOSS]: 0.1828 [G LOSS]: 4.6090 [D Acc REAL]: 89.00% [D Acc FAKE]: 8.21% [D Acc REAL - TEST]: 88.86%",
        "[D LOSS]: 0.1880 [G LOSS]: 4.6084 [D Acc REAL]: 88.88% [D Acc FAKE]: 8.54% [D Acc REAL - TEST]: 70.71%",
        "[D LOSS]: 0.2074 [G LOSS]: 4.5336 [D Acc REAL]: 88.52% [D Acc FAKE]: 8.74% [D Acc REAL - TEST]: 48.59%",
        "[D LOSS]: 0.1915 [G LOSS]: 4.6108 [D Acc REAL]: 88.85% [D Acc FAKE]: 8.73% [D Acc REAL - TEST]: 80.27%",
        "[D LOSS]: 0.1686 [G LOSS]: 4.5879 [D Acc REAL]: 89.51% [D Acc FAKE]: 7.71% [D Acc REAL - TEST]: 95.98%",
        "[D LOSS]: 0.1813 [G LOSS]: 4.6653 [D Acc REAL]: 89.04% [D Acc FAKE]: 8.30% [D Acc REAL - TEST]: 72.73%",
        "[D LOSS]: 0.1912 [G LOSS]: 4.7019 [D Acc REAL]: 88.84% [D Acc FAKE]: 8.58% [D Acc REAL - TEST]: 92.65%",
        "[D LOSS]: 0.1968 [G LOSS]: 4.5134 [D Acc REAL]: 88.86% [D Acc FAKE]: 8.67% [D Acc REAL - TEST]: 99.04%",
        "[D LOSS]: 0.1943 [G LOSS]: 4.6921 [D Acc REAL]: 88.77% [D Acc FAKE]: 8.77% [D Acc REAL - TEST]: 96.52%",
        "[D LOSS]: 0.1797 [G LOSS]: 4.5800 [D Acc REAL]: 89.27% [D Acc FAKE]: 8.16% [D Acc REAL - TEST]: 84.76%",
        "[D LOSS]: 0.2039 [G LOSS]: 4.5815 [D Acc REAL]: 88.85% [D Acc FAKE]: 8.60% [D Acc REAL - TEST]: 72.89%",
        "[D LOSS]: 0.1868 [G LOSS]: 4.5561 [D Acc REAL]: 89.02% [D Acc FAKE]: 8.50% [D Acc REAL - TEST]: 80.07%",
        "[D LOSS]: 0.2019 [G LOSS]: 4.6943 [D Acc REAL]: 88.69% [D Acc FAKE]: 8.67% [D Acc REAL - TEST]: 57.99%",
        "[D LOSS]: 0.1853 [G LOSS]: 4.5736 [D Acc REAL]: 89.05% [D Acc FAKE]: 8.43% [D Acc REAL - TEST]: 86.52%",
        "[D LOSS]: 0.1814 [G LOSS]: 4.6074 [D Acc REAL]: 89.13% [D Acc FAKE]: 8.31% [D Acc REAL - TEST]: 60.99%",
        "[D LOSS]: 0.1622 [G LOSS]: 4.6959 [D Acc REAL]: 90.10% [D Acc FAKE]: 7.62% [D Acc REAL - TEST]: 88.12%",
        "[D LOSS]: 0.1899 [G LOSS]: 4.7207 [D Acc REAL]: 89.23% [D Acc FAKE]: 8.19% [D Acc REAL - TEST]: 65.47%",
        "[D LOSS]: 0.1945 [G LOSS]: 4.6412 [D Acc REAL]: 88.76% [D Acc FAKE]: 8.61% [D Acc REAL - TEST]: 73.95%",
        "[D LOSS]: 0.1771 [G LOSS]: 4.6674 [D Acc REAL]: 89.43% [D Acc FAKE]: 8.04% [D Acc REAL - TEST]: 73.82%",
        "[D LOSS]: 0.1797 [G LOSS]: 4.7077 [D Acc REAL]: 89.33% [D Acc FAKE]: 8.16% [D Acc REAL - TEST]: 80.29%",
        "[D LOSS]: 0.1775 [G LOSS]: 4.7996 [D Acc REAL]: 89.57% [D Acc FAKE]: 8.15% [D Acc REAL - TEST]: 61.76%",
        "[D LOSS]: 0.1882 [G LOSS]: 4.7897 [D Acc REAL]: 89.16% [D Acc FAKE]: 8.39% [D Acc REAL - TEST]: 63.05%",
        "[D LOSS]: 0.1813 [G LOSS]: 4.7467 [D Acc REAL]: 89.25% [D Acc FAKE]: 8.41% [D Acc REAL - TEST]: 69.62%",
        "[D LOSS]: 0.2061 [G LOSS]: 4.7114 [D Acc REAL]: 88.41% [D Acc FAKE]: 8.92% [D Acc REAL - TEST]: 61.41%",
        "[D LOSS]: 0.1559 [G LOSS]: 4.6951 [D Acc REAL]: 90.14% [D Acc FAKE]: 7.70% [D Acc REAL - TEST]: 96.77%",
        "[D LOSS]: 0.1825 [G LOSS]: 4.8160 [D Acc REAL]: 89.55% [D Acc FAKE]: 7.99% [D Acc REAL - TEST]: 62.94%",
        "[D LOSS]: 0.1893 [G LOSS]: 4.8334 [D Acc REAL]: 89.13% [D Acc FAKE]: 8.21% [D Acc REAL - TEST]: 96.15%",
        "[D LOSS]: 0.1741 [G LOSS]: 4.7092 [D Acc REAL]: 89.68% [D Acc FAKE]: 7.63% [D Acc REAL - TEST]: 64.21%",
        "[D LOSS]: 0.1728 [G LOSS]: 4.8192 [D Acc REAL]: 89.63% [D Acc FAKE]: 7.90% [D Acc REAL - TEST]: 90.28%",
        "[D LOSS]: 0.1882 [G LOSS]: 4.8506 [D Acc REAL]: 89.34% [D Acc FAKE]: 8.12% [D Acc REAL - TEST]: 72.15%",
        "[D LOSS]: 0.1759 [G LOSS]: 4.8579 [D Acc REAL]: 89.53% [D Acc FAKE]: 7.95% [D Acc REAL - TEST]: 93.48%",
        "[D LOSS]: 0.1743 [G LOSS]: 4.7675 [D Acc REAL]: 89.68% [D Acc FAKE]: 7.82% [D Acc REAL - TEST]: 74.82%",
        "[D LOSS]: 0.1902 [G LOSS]: 4.7614 [D Acc REAL]: 88.91% [D Acc FAKE]: 8.56% [D Acc REAL - TEST]: 87.78%",
        "[D LOSS]: 0.1784 [G LOSS]: 4.7341 [D Acc REAL]: 89.49% [D Acc FAKE]: 8.00% [D Acc REAL - TEST]: 72.26%",
        "[D LOSS]: 0.1848 [G LOSS]: 4.7033 [D Acc REAL]: 89.09% [D Acc FAKE]: 8.45% [D Acc REAL - TEST]: 92.01%",
        "[D LOSS]: 0.1675 [G LOSS]: 4.8636 [D Acc REAL]: 90.06% [D Acc FAKE]: 7.54% [D Acc REAL - TEST]: 78.82%",
        "[D LOSS]: 0.1730 [G LOSS]: 4.8927 [D Acc REAL]: 89.72% [D Acc FAKE]: 7.64% [D Acc REAL - TEST]: 95.42%",
        "[D LOSS]: 0.1806 [G LOSS]: 4.8790 [D Acc REAL]: 89.41% [D Acc FAKE]: 7.83% [D Acc REAL - TEST]: 60.46%",
        "[D LOSS]: 0.1717 [G LOSS]: 4.9106 [D Acc REAL]: 89.90% [D Acc FAKE]: 7.47% [D Acc REAL - TEST]: 78.94%",
        "[D LOSS]: 0.1870 [G LOSS]: 4.8836 [D Acc REAL]: 89.16% [D Acc FAKE]: 8.07% [D Acc REAL - TEST]: 59.81%",
        "[D LOSS]: 0.1739 [G LOSS]: 4.7648 [D Acc REAL]: 89.73% [D Acc FAKE]: 7.79% [D Acc REAL - TEST]: 97.19%",
        "[D LOSS]: 0.1907 [G LOSS]: 4.8407 [D Acc REAL]: 89.27% [D Acc FAKE]: 8.23% [D Acc REAL - TEST]: 72.59%",
        "[D LOSS]: 0.1687 [G LOSS]: 4.8305 [D Acc REAL]: 89.98% [D Acc FAKE]: 7.46% [D Acc REAL - TEST]: 26.34%",
        "[D LOSS]: 0.1798 [G LOSS]: 4.9292 [D Acc REAL]: 89.68% [D Acc FAKE]: 7.77% [D Acc REAL - TEST]: 60.84%",
        "[D LOSS]: 0.1687 [G LOSS]: 4.8212 [D Acc REAL]: 89.97% [D Acc FAKE]: 7.40% [D Acc REAL - TEST]: 70.51%",
        "[D LOSS]: 0.1727 [G LOSS]: 4.8397 [D Acc REAL]: 89.91% [D Acc FAKE]: 7.49% [D Acc REAL - TEST]: 96.28%",
        "[D LOSS]: 0.1755 [G LOSS]: 4.8535 [D Acc REAL]: 89.72% [D Acc FAKE]: 7.65% [D Acc REAL - TEST]: 17.47%",
        "[D LOSS]: 0.1651 [G LOSS]: 4.9147 [D Acc REAL]: 90.10% [D Acc FAKE]: 7.29% [D Acc REAL - TEST]: 80.44%",
        "[D LOSS]: 0.1857 [G LOSS]: 4.9031 [D Acc REAL]: 89.44% [D Acc FAKE]: 8.09% [D Acc REAL - TEST]: 76.15%",
        "[D LOSS]: 0.1759 [G LOSS]: 4.7774 [D Acc REAL]: 89.84% [D Acc FAKE]: 7.82% [D Acc REAL - TEST]: 82.89%",
        "[D LOSS]: 0.1785 [G LOSS]: 4.9250 [D Acc REAL]: 89.85% [D Acc FAKE]: 7.74% [D Acc REAL - TEST]: 80.08%"
    ]
}